implib/__init__.py
implib/facetbody.py
implib/mathext.py
implib/tar.py
implib/cutting/__init__.py
implib/cutting/cutcmds.py
implib/cutting/cutfile.py
implib/cutting/cutfileparsers.py
implib/tplan/__init__.py
implib/tplan/case.py
implib/tplan/robfile.py
implib-1.0a3.dist-info/DESCRIPTION.rst
implib-1.0a3.dist-info/METADATA
implib-1.0a3.dist-info/RECORD
implib-1.0a3.dist-info/WHEEL
implib-1.0a3.dist-info/metadata.json
implib-1.0a3.dist-info/top_level.txt
