Metadata-Version: 2.0
Name: implib
Version: 1.0a3
Summary: Python library for the Implant Group at Think Surgical Inc.
Home-page: http://stash/projects/IMP/repos/implibpythonpackage/browse/implib
Author: C.J. Geering
Author-email: cgeering@thinksurgical.com
License: Proprietary License, Copyright (c) 2017, Think Surgical Inc.
Requires-Dist: numpy (>=1.13.1)
Requires-Dist: vtk (>=7.1.1)
